mlrl/__init__.py
mlrl/testbed/__init__.py
mlrl/testbed/arguments.py
mlrl/testbed/command.py
mlrl/testbed/main.py
mlrl/testbed/program_info.py
mlrl/testbed/runnables.py
mlrl/testbed/experiments/__init__.py
mlrl/testbed/experiments/context.py
mlrl/testbed/experiments/data.py
mlrl/testbed/experiments/dataset.py
mlrl/testbed/experiments/dataset_type.py
mlrl/testbed/experiments/experiment.py
mlrl/testbed/experiments/file_path.py
mlrl/testbed/experiments/fold.py
mlrl/testbed/experiments/meta_data.py
mlrl/testbed/experiments/prediction_scope.py
mlrl/testbed/experiments/prediction_type.py
mlrl/testbed/experiments/problem_domain.py
mlrl/testbed/experiments/recipe.py
mlrl/testbed/experiments/state.py
mlrl/testbed/experiments/table.py
mlrl/testbed/experiments/timer.py
mlrl/testbed/experiments/input/__init__.py
mlrl/testbed/experiments/input/arguments.py
mlrl/testbed/experiments/input/data.py
mlrl/testbed/experiments/input/extension.py
mlrl/testbed/experiments/input/policies.py
mlrl/testbed/experiments/input/reader.py
mlrl/testbed/experiments/input/dataset/__init__.py
mlrl/testbed/experiments/input/dataset/arguments.py
mlrl/testbed/experiments/input/dataset/dataset.py
mlrl/testbed/experiments/input/dataset/extension.py
mlrl/testbed/experiments/input/dataset/reader.py
mlrl/testbed/experiments/input/dataset/preprocessors/__init__.py
mlrl/testbed/experiments/input/dataset/preprocessors/preprocessor.py
mlrl/testbed/experiments/input/dataset/splitters/__init__.py
mlrl/testbed/experiments/input/dataset/splitters/arguments.py
mlrl/testbed/experiments/input/dataset/splitters/splitter.py
mlrl/testbed/experiments/input/dataset/splitters/splitter_no.py
mlrl/testbed/experiments/input/meta_data/__init__.py
mlrl/testbed/experiments/input/meta_data/meta_data.py
mlrl/testbed/experiments/input/meta_data/metadata.schema.yml
mlrl/testbed/experiments/input/meta_data/reader.py
mlrl/testbed/experiments/input/model/__init__.py
mlrl/testbed/experiments/input/model/extension.py
mlrl_testbed-0.15.1.dist-info/METADATA
mlrl_testbed-0.15.1.dist-info/WHEEL
mlrl_testbed-0.15.1.dist-info/entry_points.txt
mlrl_testbed-0.15.1.dist-info/top_level.txt
mlrl_testbed-0.15.1.dist-info/RECORD
