Metadata-Version: 2.4
Name: mlrl-testbed
Version: 0.15.1
Summary: Provides utilities for the training and evaluation of machine learning algorithms
Author-email: Michael Rapp <michael.rapp.ml@gmail.com>
License-Expression: MIT
Project-URL: homepage, https://github.com/mrapp-ke/MLRL-Boomer
Project-URL: source, https://github.com/mrapp-ke/MLRL-Boomer.git
Project-URL: download, https://github.com/mrapp-ke/MLRL-Boomer/releases
Project-URL: changelog, https://raw.githubusercontent.com/mrapp-ke/MLRL-Boomer/refs/heads/main/CHANGELOG.md
Project-URL: documentation, https://mlrl-boomer.readthedocs.io/en/latest
Project-URL: issues, https://github.com/mrapp-ke/MLRL-Boomer/issues
Keywords: machine learning,multi-label classification,multi-output regression,multi-target regression
Classifier: Development Status :: 5 - Production/Stable
Classifier: Intended Audience :: Science/Research
Classifier: Operating System :: OS Independent
Classifier: Programming Language :: Python :: 3
Classifier: Topic :: Scientific/Engineering :: Artificial Intelligence
Classifier: Topic :: Software Development :: Libraries :: Python Modules
Requires-Python: >=3.12
Requires-Dist: mlrl-util==0.15.1
Requires-Dist: pyyaml<6.1,>=6.0
Requires-Dist: tabulate<0.10,>=0.9
Requires-Dist: yamale<6.2,>=6.1
Provides-Extra: testbed
Requires-Dist: mlrl-testbed-sklearn==0.15.1; extra == "testbed"
Requires-Dist: mlrl-testbed-slurm==0.15.1; extra == "testbed"
